sqlalchemy_uuidstr/__init__.py
sqlalchemy_uuidstr-0.0.2.dist-info/METADATA
sqlalchemy_uuidstr-0.0.2.dist-info/WHEEL
sqlalchemy_uuidstr-0.0.2.dist-info/top_level.txt
sqlalchemy_uuidstr-0.0.2.dist-info/RECORD
